regression_model/VERSION
regression_model/__init__.py
regression_model/config.yml
regression_model/pipeline.py
regression_model/predict.py
regression_model/train_pipeline.py
regression_model/config/__init__.py
regression_model/config/core.py
regression_model/datasets/__init__.py
regression_model/processing/__init__.py
regression_model/processing/data_manager.py
regression_model/processing/features.py
regression_model/processing/validation.py
regression_model/trained_models/__init__.py
somorrostro_regression_model-0.0.4.dist-info/METADATA
somorrostro_regression_model-0.0.4.dist-info/WHEEL
somorrostro_regression_model-0.0.4.dist-info/top_level.txt
somorrostro_regression_model-0.0.4.dist-info/RECORD
