Metadata-Version: 2.1
Name: somorrostro-regression-model
Version: 0.0.4
Summary: Example regression model for IAB Somorrostro
Home-page: https://gitlab.com/mikel_diez/regression_prod_example
Author: Mikel Diez Garcia
Author-email: mikel.diez@somorrostro.com
License: BSD-3
Classifier: License :: OSI Approved :: MIT License
Classifier: Programming Language :: Python
Classifier: Programming Language :: Python :: 3
Classifier: Programming Language :: Python :: 3.6
Classifier: Programming Language :: Python :: 3.7
Classifier: Programming Language :: Python :: 3.8
Classifier: Programming Language :: Python :: 3.9
Classifier: Programming Language :: Python :: Implementation :: CPython
Classifier: Programming Language :: Python :: Implementation :: PyPy
Requires-Python: >=3.6.0
Requires-Dist: numpy ==1.21.0
Requires-Dist: pandas ==1.3.5
Requires-Dist: pydantic ==1.8.1
Requires-Dist: scikit-learn ==1.1.3
Requires-Dist: strictyaml ==1.3.2
Requires-Dist: ruamel.yaml ==0.16.2
Requires-Dist: feature-engine ==1.0.2
Requires-Dist: joblib ==1.0.1
